lazerpay/__init__.py
lazerpay/_http_client.py
lazerpay/lazerpay.py
lazerpay/services/__init__.py
lazerpay/services/misc.py
lazerpay/services/payment.py
lazerpay/services/paymentlinks.py
lazerpay/utils/__init__.py
lazerpay/utils/constants.py
lazerpay_sdk-1.0.0.dist-info/METADATA
lazerpay_sdk-1.0.0.dist-info/WHEEL
lazerpay_sdk-1.0.0.dist-info/top_level.txt
lazerpay_sdk-1.0.0.dist-info/RECORD
